langchain_cli/__init__.py
langchain_cli/cli.py
langchain_cli/constants.py
langchain_cli/dev_scripts.py
langchain_cli/integration_template/.gitignore
langchain_cli/integration_template/LICENSE
langchain_cli/integration_template/Makefile
langchain_cli/integration_template/README.md
langchain_cli/integration_template/docs/chat.ipynb
langchain_cli/integration_template/docs/document_loaders.ipynb
langchain_cli/integration_template/docs/llms.ipynb
langchain_cli/integration_template/docs/provider.ipynb
langchain_cli/integration_template/docs/retrievers.ipynb
langchain_cli/integration_template/docs/stores.ipynb
langchain_cli/integration_template/docs/text_embedding.ipynb
langchain_cli/integration_template/docs/toolkits.ipynb
langchain_cli/integration_template/docs/tools.ipynb
langchain_cli/integration_template/docs/vectorstores.ipynb
langchain_cli/integration_template/integration_template/__init__.py
langchain_cli/integration_template/integration_template/chat_models.py
langchain_cli/integration_template/integration_template/document_loaders.py
langchain_cli/integration_template/integration_template/embeddings.py
langchain_cli/integration_template/integration_template/llms.py
langchain_cli/integration_template/integration_template/py.typed
langchain_cli/integration_template/integration_template/retrievers.py
langchain_cli/integration_template/integration_template/toolkits.py
langchain_cli/integration_template/integration_template/tools.py
langchain_cli/integration_template/integration_template/vectorstores.py
langchain_cli/integration_template/pyproject.toml
langchain_cli/integration_template/scripts/check_imports.py
langchain_cli/integration_template/scripts/check_pydantic.sh
langchain_cli/integration_template/scripts/lint_imports.sh
langchain_cli/integration_template/tests/__init__.py
langchain_cli/integration_template/tests/integration_tests/__init__.py
langchain_cli/integration_template/tests/integration_tests/test_chat_models.py
gigachain_cli-0.0.30.post1.dist-info/LICENSE
gigachain_cli-0.0.30.post1.dist-info/METADATA
gigachain_cli-0.0.30.post1.dist-info/WHEEL
gigachain_cli-0.0.30.post1.dist-info/entry_points.txt
gigachain_cli-0.0.30.post1.dist-info/RECORD
